{
  "lang": "en-US",
  "example": "feat(DESIGNSYS-9999): add new component",
  "types": {
    "feat": "Добавление нового функционала",
    "fix": "Исправление ошибок",
    "build": "Сборка проекта или изменения внешних зависимостей",
    "docs": "Обновление документации",
    "style": "Правки по кодстайлу (табы, отступы, точки, запятые и т.д.)",
    "refactor": "Правки кода без исправления ошибок или добавления новых функций",
    "perf": "Изменения направленные на улучшение производительности",
    "ci": "Настройка CI и работа со скриптами",
    "test": "Добавление тестов",
    "chore": "Изменения не относящиеся к изменению производственного кода (изменения в конфигах, как пример .gitignore)",
    "temp": false,
    "deps": false
  },
  "max-len": 72,
  "scopeDescriptions": [
    "Здесь должен быть указан номер задачи"
  ],
  "subjectDescriptions": [
    "Здесь указываются изменения проекта, произведенные в коммите"
  ],
  "showInvalidHeader": true,
  "scopeRequired": true
}
