{
  "100%-opacity": {
    "value": "100%",
    "type": "opacity"
  },
  "95%-opacity": {
    "value": "95%",
    "type": "opacity"
  },
  "85%-opacity": {
    "value": "85%",
    "type": "opacity"
  },
  "75%-opacity": {
    "value": "75%",
    "type": "opacity"
  },
  "65%-opacity": {
    "value": "65%",
    "type": "opacity"
  },
  "50%-opacity": {
    "value": "50%",
    "type": "opacity"
  },
  "45%-opacity": {
    "value": "45%",
    "type": "opacity"
  },
  "35%-opacity": {
    "value": "35%",
    "type": "opacity"
  },
  "25%-opacity": {
    "value": "25%",
    "type": "opacity"
  },
  "15%-opacity": {
    "value": "15%",
    "type": "opacity"
  },
  "5%-opacity": {
    "value": "5%",
    "type": "opacity"
  },
  "8%-opacity": {
    "value": "8%",
    "type": "opacity"
  }
}